episoder/__init__.py
episoder/database.py
episoder/episoder.py
episoder/main.py
episoder/output.py
episoder/version.py
episoder/sources/__init__.py
episoder/sources/epguides.py
episoder/sources/parser.py
episoder/sources/thetvdb.py
episoder/sources/tvcom.py
episoder-0.11.0.dist-info/COPYING
episoder-0.11.0.dist-info/METADATA
episoder-0.11.0.dist-info/WHEEL
episoder-0.11.0.dist-info/entry_points.txt
episoder-0.11.0.dist-info/top_level.txt
episoder-0.11.0.dist-info/RECORD
