Metadata-Version: 2.1
Name: episoder
Version: 0.11.0
Summary: TV episode notifier
Home-page: https://code.ott.net/episoder/
Author: Stefan Ott
Author-email: stefan@ott.net
Project-URL: Source, https://git.ott.net/episoder/
Classifier: Development Status :: 5 - Production/Stable
Classifier: Environment :: Console
Classifier: Intended Audience :: End Users/Desktop
Classifier: License :: OSI Approved :: GNU General Public License v3 or later (GPLv3+)
Classifier: Natural Language :: English
Classifier: Operating System :: OS Independent
Classifier: Programming Language :: Python
Classifier: Topic :: Multimedia :: Video
Requires-Python: >=3.6
License-File: COPYING
Requires-Dist: argparse
Requires-Dist: requests
Requires-Dist: beautifulsoup4
Requires-Dist: sqlalchemy >=1.3
